CHANGELOG.md
slack_time_localization_bot/__init__.py
slack_time_localization_bot/app.py
slack_time_localization_bot/cli.py
slack_time_localization_bot/parsing.py
slack_time_localization_bot/utils.py
slack_time_localization_bot-0.1.12.dist-info/LICENSE
slack_time_localization_bot-0.1.12.dist-info/METADATA
slack_time_localization_bot-0.1.12.dist-info/WHEEL
slack_time_localization_bot-0.1.12.dist-info/entry_points.txt
slack_time_localization_bot-0.1.12.dist-info/RECORD
