Metadata-Version: 2.1
Name: slack-time-localization-bot
Version: 0.1.12
Summary: Detect temporal expressions in Slack messages ("tomorrow at 5 pm") and translate them for readers in other timezones.
Home-page: https://github.com/Slack-Time-Localization-Bot/Slack-Time-Localization-Bot
License: MIT
Author: Philipp Hossner
Author-email: philipp.hossner@posteo.de
Requires-Python: >=3.8,<4.0
Classifier: License :: OSI Approved :: MIT License
Classifier: Programming Language :: Python :: 3
Classifier: Programming Language :: Python :: 3.8
Classifier: Programming Language :: Python :: 3.9
Classifier: Programming Language :: Python :: 3.10
Classifier: Programming Language :: Python :: 3.11
Classifier: Programming Language :: Python :: 3.12
Requires-Dist: cachetools (>=5.3.2,<6.0.0)
Requires-Dist: freezegun (>=1.5.1,<2.0.0)
Requires-Dist: lingua-language-detector (>=2.0.2,<3.0.0)
Requires-Dist: pendulum (>=3.0.0,<4.0.0)
Requires-Dist: pyduckling-native-phihos (>=0.2.0,<0.3.0)
Requires-Dist: regex (>=2024.5.15,<2025.0.0)
Requires-Dist: slack-bolt (>=1.18.1,<2.0.0)
Requires-Dist: typer[all] (>=0.9,<0.13)
Project-URL: Repository, https://github.com/Slack-Time-Localization-Bot/Slack-Time-Localization-Bot
